nullable/__init__.py
nullable/py.typed
nullable-0.2.0.dist-info/LICENSE
nullable-0.2.0.dist-info/METADATA
nullable-0.2.0.dist-info/WHEEL
nullable-0.2.0.dist-info/RECORD
