Metadata-Version: 2.1
Name: nullable
Version: 0.2.0
Summary: Typed Null support
License: MIT
Author: CircuitSacul
Author-email: circuitsacul@icloud.com
Requires-Python: >=3.8,<4.0
Classifier: License :: OSI Approved :: MIT License
Classifier: Programming Language :: Python :: 3
Classifier: Programming Language :: Python :: 3.8
Classifier: Programming Language :: Python :: 3.9
Classifier: Programming Language :: Python :: 3.10
Classifier: Programming Language :: Python :: 3.11
